pycreator/__init__.py
pycreator/actions/__init__.py
pycreator/actions/action.py
pycreator/actions/action_dispatcher.py
pycreator/actions/version.py
pycreator/actions/add/__init__.py
pycreator/actions/add/add_action.py
pycreator/actions/create/__init__.py
pycreator/actions/create/create_action.py
pycreator/actions/goes/__init__.py
pycreator/actions/goes/goes_action.py
pycreator/core/__init__.py
pycreator/core/create_folders.py
pycreator/core/template.py
pycreator/framework/__init__.py
pycreator/framework/messages.py
pycreator/main/__init__.py
pycreator/main/main.py
pycreator/templates/__init__.py
pycreator/templates/action.j2
pycreator/templates/action_dispatcher.j2
pycreator/templates/example_action.j2
pycreator/templates/main.j2
pycreator/templates/messages.j2
pycreator/templates/setup.j2
pycreator/templates/version.j2
pycreator-0.2.2.dist-info/METADATA
pycreator-0.2.2.dist-info/WHEEL
pycreator-0.2.2.dist-info/entry_points.txt
pycreator-0.2.2.dist-info/top_level.txt
pycreator-0.2.2.dist-info/RECORD
