Metadata-Version: 2.1
Name: pycreator
Version: 0.2.2
Summary: Automatically create a command application
Home-page: https://github.com/NexSabre/pycreator
Author: Nex Sabre
Author-email: nexsabre@protonmail.com
License: UNKNOWN
Platform: UNKNOWN
Classifier: Programming Language :: Python :: 3
Classifier: License :: OSI Approved :: MIT License
Requires-Python: >=3.6
Requires-Dist: jinja2 (~=2.11)
